openassistants_fastapi/__init__.py
openassistants_fastapi/py.typed
openassistants_fastapi/routes.py
openassistants_fastapi/utils/sse.py
definitive_openassistants_fastapi-0.0.14.dist-info/METADATA
definitive_openassistants_fastapi-0.0.14.dist-info/WHEEL
definitive_openassistants_fastapi-0.0.14.dist-info/RECORD
