Metadata-Version: 2.1
Name: definitive-openassistants-fastapi
Version: 0.0.14
Summary: 
Author: Rick Lamers
Author-email: ricklamers@gmail.com
Requires-Python: >=3.10,<3.12
Classifier: Programming Language :: Python :: 3
Classifier: Programming Language :: Python :: 3.10
Classifier: Programming Language :: Python :: 3.11
Requires-Dist: fastapi (>=0.109.2,<0.110.0)
Requires-Dist: langchain (>=0.0.352,<0.0.353)
Requires-Dist: sse-starlette (>=1.8.2,<2.0.0)
Requires-Dist: starlette (==0.36.3)
